iotio_client/AsyncIoTClient.py
iotio_client/Client.py
iotio_client/Endpoint.py
iotio_client/Errors.py
iotio_client/IoTClient.py
iotio_client/PacketEncoder.py
iotio_client/__init__.py
iotio_client/__main__.py
iotio_client/types.py
iot.io_client-0.4.12.dist-info/LICENSE.md
iot.io_client-0.4.12.dist-info/METADATA
iot.io_client-0.4.12.dist-info/WHEEL
iot.io_client-0.4.12.dist-info/top_level.txt
iot.io_client-0.4.12.dist-info/RECORD
