Metadata-Version: 2.1
Name: iot.io-client
Version: 0.4.12
Summary: A client library designed for connecting to a iot.io server instance.
Home-page: https://github.com/dylancrockett/iot.io-client
Author: Dylan Crockett
Author-email: dylanrcrockett@gmail.com
License: MIT
Project-URL: Documentation, https://iotio-client.readthedocs.io/
Project-URL: Source Code, https://github.com/dylancrockett/iot.io-client
Platform: UNKNOWN
Classifier: Programming Language :: Python :: 3
Classifier: License :: OSI Approved :: MIT License
Classifier: Operating System :: OS Independent
Requires-Python: >=3.7
Requires-Dist: websockets
Requires-Dist: websocket-client
